{
  "CelebrityFaces": [],
  "UnrecognizedFaces": [
    {
      "BoundingBox": {
        "Width": 0.0205078125,
        "Height": 0.026249999180436134,
        "Left": 0.853515625,
        "Top": 0.824999988079071
      },
      "Confidence": 99.64161682128906,
      "Landmarks": [
        {
          "Type": "eyeLeft",
          "X": 0.8591897487640381,
          "Y": 0.8372565507888794
        },
        {
          "Type": "eyeRight",
          "X": 0.8663432598114014,
          "Y": 0.8353560566902161
        },
        {
          "Type": "nose",
          "X": 0.8620668053627014,
          "Y": 0.8396089673042297
        },
        {
          "Type": "mouthLeft",
          "X": 0.8604783415794373,
          "Y": 0.8481591939926147
        },
        {
          "Type": "mouthRight",
          "X": 0.8667030930519104,
          "Y": 0.8468336462974548
        }
      ],
      "Pose": {
        "Roll": -11.035148620605469,
        "Yaw": -9.11532974243164,
        "Pitch": 19.766752243041992
      },
      "Quality": {
        "Brightness": 38.2119255065918,
        "Sharpness": 7.628174304962158
      }
    }
  ],
  "OrientationCorrection": "ROTATE_0"
}
