{
  "responses": [
    {
      "webDetection": {
        "bestGuessLabels": [
          {
            "label": "feather and two stones",
            "languageCode": "en"
          }
        ],
        "visuallySimilarImages": [
          {
            "url": "https://shop.r10s.jp/gold/alei/sp/flickslider/semi_pinky_ks1c.jpg"
          },
          {
            "url": "https://ae01.alicdn.com/kf/HTB1oSc3SFXXXXXsapXXq6xXFXXXZ/SHUANGR-2017-New-Vintage-Retro-Peacock-Feather-Unique-Ring-Angels-For-Women-Antique-Silver-Color-Top.jpg_q50.jpg"
          },
          {
            "url": "https://derpicdn.net/img/2013/12/8/492785/full.jpg"
          },
          {
            "url": "https://static.wixstatic.com/media/95191a_554b2221d5ce4f7490b32cf0eede394d~mv2_d_2480_3508_s_4_2.jpg/v1/fit/w_498,h_704,q_90/file.webp"
          },
          {
            "url": "https://i.pinimg.com/236x/45/53/67/455367370e53ececc6bada34cea5aa3a.jpg"
          }
        ],
        "webEntities": [
          {
            "description": "Web page",
            "entityId": "/m/086nh",
            "score": 0.35363424
          },
          {
            "description": "Keats on his Deathbed",
            "entityId": "/m/0k7hxgj",
            "score": 0.31364998
          },
          {
            "description": "Feather and two stones",
            "entityId": "/g/11cktgvnqk",
            "score": 0.306
          },
          {
            "description": "Rachel de Ruvigny, Countess of Southampton",
            "entityId": "/g/11bwqnk6sf",
            "score": 0.2949
          },
          {
            "description": "Online advertising",
            "entityId": "/m/05b1rx",
            "score": 0.25932443
          },
          {
            "description": "Advertising",
            "entityId": "/m/011s0",
            "score": 0.2414
          },
          {
            "description": "Line",
            "entityId": "/m/03scnj",
            "score": 0.22321914
          },
          {
            "description": "Font",
            "entityId": "/m/03gq5hm",
            "score": 0.19797505
          },
          {
            "description": "World Wide Web",
            "entityId": "/m/0828v",
            "score": 0.1968
          },
          {
            "description": "Online and offline",
            "entityId": "/m/0bcp7",
            "score": 0.1795
          }
        ]
      }
    }
  ]
}
